jatoolbox/__init__.py
jatoolbox/jatoolbox.py
JATOOLBOX-1.0.0.dist-info/LICENSE
JATOOLBOX-1.0.0.dist-info/METADATA
JATOOLBOX-1.0.0.dist-info/WHEEL
JATOOLBOX-1.0.0.dist-info/top_level.txt
JATOOLBOX-1.0.0.dist-info/RECORD
